xbrain/__init__.py
xbrain/core/__init__.py
xbrain/core/agent.py
xbrain/core/agent_ui.py
xbrain/core/chat.py
xbrain/core/context.py
xbrain/core/tool.py
xbrain/utils/__init__.py
xbrain/utils/config.py
xbrain/utils/input_util.py
xbrain/utils/openai_utils.py
pyxbrain-2.0.8.dist-info/METADATA
pyxbrain-2.0.8.dist-info/WHEEL
pyxbrain-2.0.8.dist-info/top_level.txt
pyxbrain-2.0.8.dist-info/RECORD
