Metadata-Version: 2.4
Name: pyxbrain
Version: 2.0.8
Summary: 极简的智能体开发框架
Requires-Dist: pyyaml==6.0.2
Requires-Dist: openai==2.8.1
Dynamic: description
Dynamic: description-content-type
Dynamic: requires-dist
Dynamic: summary
